setup.cfg
setup.py
pyniland/__init__.py
pyniland/client.py
pyniland/exceptions.py
pyniland.egg-info/PKG-INFO
pyniland.egg-info/SOURCES.txt
pyniland.egg-info/dependency_links.txt
pyniland.egg-info/requires.txt
pyniland.egg-info/top_level.txt