Metadata-Version: 1.1
Name: pyniland
Version: 1.0.1
Summary: Niland API Client for Python
Home-page: https://github.com/niland/api-client-python
Author: Niland Team
Author-email: support@niland.io
License: MIT License
Keywords: niland,pyniland,music,search,recommendation,hosted,cloud,tagging
Platform: UNKNOWN
Classifier: Intended Audience :: Developers
Classifier: License :: OSI Approved :: MIT License
Classifier: Operating System :: OS Independent
Classifier: Programming Language :: Python
Classifier: Programming Language :: Python :: 2
Classifier: Programming Language :: Python :: 2.6
Classifier: Programming Language :: Python :: 2.7
Classifier: Topic :: Internet
Classifier: Topic :: Internet :: WWW/HTTP
Classifier: Topic :: Internet :: WWW/HTTP :: Indexing/Search
Classifier: Development Status :: 5 - Production/Stable
